miragic_sdk/__init__.py
miragic_sdk/api_client.py
miragic_sdk/background_removal.py
miragic_sdk/blur_background.py
miragic_sdk/cli.py
miragic_sdk/core.py
miragic_sdk/image_upscaler.py
miragic_sdk-1.0.2.dist-info/licenses/LICENSE
miragic_sdk-1.0.2.dist-info/METADATA
miragic_sdk-1.0.2.dist-info/WHEEL
miragic_sdk-1.0.2.dist-info/entry_points.txt
miragic_sdk-1.0.2.dist-info/top_level.txt
miragic_sdk-1.0.2.dist-info/RECORD
