Metadata-Version: 2.4
Name: miragic-sdk
Version: 1.0.2
Summary: Advanced image processing SDK with background removal, upscaling, and blur effects
Author-email: Miragic Team <info@miragic.ai>
Maintainer-email: Miragic Team <info@miragic.ai>
License: MIT License
Project-URL: Homepage, https://miragic.ai
Project-URL: Documentation, https://docs.miragic.ai
Project-URL: Repository, https://github.com/miragic/miragic-sdk
Project-URL: Bug Tracker, https://github.com/miragic/miragic-sdk/issues
Keywords: image processing,background removal,upscaling,blur,AI,computer vision
Classifier: Development Status :: 5 - Production/Stable
Classifier: Intended Audience :: Developers
Classifier: Topic :: Software Development :: Libraries :: Python Modules
Classifier: Topic :: Multimedia :: Graphics :: Graphics Conversion
Classifier: Topic :: Scientific/Engineering :: Image Processing
Classifier: License :: OSI Approved :: MIT License
Classifier: Programming Language :: Python :: 3
Classifier: Programming Language :: Python :: 3.7
Classifier: Programming Language :: Python :: 3.8
Classifier: Programming Language :: Python :: 3.9
Classifier: Programming Language :: Python :: 3.10
Classifier: Programming Language :: Python :: 3.11
Classifier: Programming Language :: Python :: 3.12
Classifier: Operating System :: OS Independent
Requires-Python: >=3.7
License-File: LICENSE
Requires-Dist: Pillow>=8.0.0
Requires-Dist: numpy>=1.19.0
Requires-Dist: requests>=2.25.0
Provides-Extra: dev
Requires-Dist: pytest>=6.0; extra == "dev"
Requires-Dist: pytest-cov>=2.0; extra == "dev"
Requires-Dist: black>=21.0; extra == "dev"
Requires-Dist: flake8>=3.8; extra == "dev"
Requires-Dist: mypy>=0.800; extra == "dev"
Provides-Extra: docs
Requires-Dist: sphinx>=4.0; extra == "docs"
Requires-Dist: sphinx-rtd-theme>=1.0; extra == "docs"
Dynamic: license-file
